[
    {
        "name":"Sexo",
        "options": ["Masculino","Femenino","Otro"]
    },
    {
        "name":"Estado Civil",
        "options": ["Soltero","Casado","Divorciado","Viudo","Unión Libre"]
    },
    {
        "name":"Nivel Educativo",
        "options": ["Primaria Incompleta","Primaria Completa","Secundaria Incompleta","Secundaria Completa","Técnico","Tecnólogo","Pregrado","Posgrado"]
    },
    {
        "name":"Tipo de documento",
        "options": ["Cédula","Cédula de Extranjería","Pasaporte","CURP"]
    },
    {
        "name":"Parentezco Familiar",
        "options": ["Cónyuge","Hermano/a","Hijo/a","Nieto/a","Sobrino/a"]
    },
    {
        "name":"Estrato Socioeconómico",
        "options": ["1","2","3","4","5","6"]
    },
    {
        "name":"Regimen de seguridad social",
        "options": ["Contributivo","Subsidiado","Vinculado","Especial","ISSTE","IMSS","Ninguno"]
    },
    {
        "name":"Antecedentes Farmacológicos",
        "options": ["Analgésicos","Insulina","Antiagregantes plaquetarios","Antidepresivos","Antirreumáticos","AINES","Relajante Muscular","Antihipertensivos","Anticonvulsivos","Protector gástrico","Inmunosupresor","Hormona Tiroidea","Estatinas","Antiparkinsonianos"]
    }
]